Workbook

Sheet Prediction Sheet
A1: Cheese | B1: Cost per Kilo in Euros | C1: Average monthly sales based on Euro to Pound exchange rate of 0.7 | D1: Selling Price in GBP | E1: Cost in GBP | F1: Profit Margin | G1: Profit in GBP
A2: Camembert | B2: 28 | C2: =IF($B$11=0.1, 'Base Sheet '!C2-20, 'Base Sheet '!C2) -> 880 | D2: =(E2*$B$13)+E2 -> 27.44 | E2: =B2*$B$12 -> 19.6 | F2: =E2*$B$13 -> 7.84 | G2: =(D2-E2)*C2 -> 6899.2
A3: Emmental | B3: 32 | C3: =IF($B$11=0.1, 'Base Sheet '!C3-20, 'Base Sheet '!C3) -> 830 | D3: =(E3*$B$13)+E3 -> 31.36 | E3: =B3*$B$12 -> 22.4 | F3: =E3*$B$13 -> 8.96 | G3: =(D3-E3)*C3 -> 7436.8
A4: Gruyere | B4: 35 | C4: =IF($B$11=0.1, 'Base Sheet '!C4-20, 'Base Sheet '!C4) -> 855 | D4: =(E4*$B$13)+E4 -> 34.3 | E4: =B4*$B$12 -> 24.5 | F4: =E4*$B$13 -> 9.8 | G4: =(D4-E4)*C4 -> 8379
A5: Edam | B5: 29 | C5: =IF($B$11=0.1, 'Base Sheet '!C5-20, 'Base Sheet '!C5) -> 805 | D5: =(E5*$B$13)+E5 -> 28.42 | E5: =B5*$B$12 -> 20.3 | F5: =E5*$B$13 -> 8.12 | G5: =(D5-E5)*C5 -> 6536.6
A6: Gouda | B6: 31 | C6: =IF($B$11=0.1, 'Base Sheet '!C6-20, 'Base Sheet '!C6) -> 680 | D6: =(E6*$B$13)+E6 -> 30.38 | E6: =B6*$B$12 -> 21.7 | F6: =E6*$B$13 -> 8.68 | G6: =(D6-E6)*C6 -> 5902.4
A11: Increment | B11: 0.1
A12: Exchange Rate | B12: 0.7 | E12: Total Profit
A13: Margin | B13: 0.4 | E13: =SUM(G2:G6) -> 35154

Sheet Base Sheet 
A1: Cheese | B1: Cost per Kilo in Euros | C1: Average monthly sales based on Euro to Pound exchange rate of 0.7 | D1: Selling Price in GBP | E1: Cost in GBP | F1: Profit Margin | G1: Profit in GBP
A2: Camembert | B2: 28 | C2: 900 | D2: =(E2*$B$13)+E2 -> 27.44 | E2: =B2*$B$12 -> 19.6 | F2: =E2*$B$13 -> 7.84 | G2: =F2*C2 -> 7056
A3: Emmental | B3: 32 | C3: 850 | D3: =(E3*$B$13)+E3 -> 31.36 | E3: =B3*$B$12 -> 22.4 | F3: =E3*$B$13 -> 8.96 | G3: =F3*C3 -> 7616
A4: Gruyere | B4: 35 | C4: 875 | D4: =(E4*$B$13)+E4 -> 34.3 | E4: =B4*$B$12 -> 24.5 | F4: =E4*$B$13 -> 9.8 | G4: =F4*C4 -> 8575
A5: Edam | B5: 29 | C5: 825 | D5: =(E5*$B$13)+E5 -> 28.42 | E5: =B5*$B$12 -> 20.3 | F5: =E5*$B$13 -> 8.12 | G5: =F5*C5 -> 6699
A6: Gouda | B6: 31 | C6: 700 | D6: =(E6*$B$13)+E6 -> 30.38 | E6: =B6*$B$12 -> 21.7 | F6: =E6*$B$13 -> 8.68 | G6: =F6*C6 -> 6076
E11: Total Profit
A12: Exchange Rate | B12: 0.7 | E12: =SUM(Table2[Profit in GBP]) -> 36022
A13: Margin | B13: 0.4

Sheet Home Page

Sheet Graphic Chart
A1: Type of Cheese | B1: Prediction Sheet Profit in GBP | C1: Base Sheet Profit in GBP
A2: Camembert | B2: 7884.8 | C2: 7056
A3: Emmental | B3: 8499.2 | C3: 7616
A4: Gruyere | B4: 9576 | C4: 8575
A5: Edam | B5: 7470.4 | C5: 6699
A6: Gouda | B6: 6745.6 | C6: 6076
A8: Total | B8: =SUM(B2:B6) -> 40176 | C8: =SUM(C2:C6) -> 36022
